email_control_ao/__init__.py
email_control_ao/infrastructure/__init__.py
email_control_ao/infrastructure/ao.py
email_control_ao/infrastructure/do.py
email_control_ao-0.0.1.dist-info/LICENSE
email_control_ao-0.0.1.dist-info/METADATA
email_control_ao-0.0.1.dist-info/WHEEL
email_control_ao-0.0.1.dist-info/top_level.txt
email_control_ao-0.0.1.dist-info/RECORD
