Metadata-Version: 2.1
Name: email-control-ao
Version: 0.0.1
Summary: Exposed interface tool for email service
Author: wangziling100
Author-email: wangziling100@163.com
Classifier: Programming Language :: Python :: 3
Classifier: License :: OSI Approved :: MIT License
License-File: LICENSE
